antishlop_cli-1.1.1.dist-info/licenses/LICENSE
antishlopcli/agent.py
antishlopcli/cli.py
antishlopcli/config.py
antishlopcli/prompts.py
antishlopcli/vector_db.py
antishlop_cli-1.1.1.dist-info/METADATA
antishlop_cli-1.1.1.dist-info/WHEEL
antishlop_cli-1.1.1.dist-info/entry_points.txt
antishlop_cli-1.1.1.dist-info/top_level.txt
antishlop_cli-1.1.1.dist-info/RECORD
