Metadata-Version: 2.4
Name: antishlop-cli
Version: 1.1.1
Summary: Anti-vibe coding and security agent
Author: Arjun Bajpai
Author-email: ArjunBajpai@tutamail.com
License-File: LICENSE
Requires-Dist: openai
Requires-Dist: colorama
Requires-Dist: rich
Requires-Dist: python-dotenv
Requires-Dist: langchain==0.3.23
Requires-Dist: langchain-openai==0.3.12
Requires-Dist: langgraph==0.2.67
Requires-Dist: typing-extensions
Requires-Dist: tiktoken
Requires-Dist: chromadb
Requires-Dist: langchain-chroma
Dynamic: author
Dynamic: author-email
Dynamic: description
Dynamic: description-content-type
Dynamic: license-file
Dynamic: requires-dist
Dynamic: summary
